onemap-0.2.2.post2.dist-info/top_level.txt
onemap-0.2.2.post2.dist-info/metadata.json
onemap-0.2.2.post2.dist-info/WHEEL
onemap-0.2.2.post2.dist-info/METADATA
onemap-0.2.2.post2.dist-info/DESCRIPTION.rst
onemap-0.2.2.post2.dist-info/RECORD
onemap/__init__.py
onemap/svy21.py
