Metadata-Version: 2.0
Name: onemap
Version: 0.2.2.post2
Summary: Wrapper for the OneMapSG API
Home-page: https://github.com/ruiwen/onemap
Author: Ruiwen Chua
Author-email: ruiwen@thoughtmonkeys.com
License: LICENSE.txt
Keywords: onemap,onemapsg
Platform: UNKNOWN
Requires-Dist: requests (>=1.2.3)
